LICENSE.txt
MANIFEST.in
README.rst
binstruct.py
setup.cfg
setup.py
binstruct.egg-info/PKG-INFO
binstruct.egg-info/SOURCES.txt
binstruct.egg-info/dependency_links.txt
binstruct.egg-info/top_level.txt
test/test_structures.py